alchemy/__init__.py
alchemy/__version__.py
alchemy/alchemy.py
alchemy/config.py
alchemy/dispatch.py
alchemy/exceptions.py
alchemy/provider.py
alchemy/types.py
alchemy/utils.py
alchemy/core/__init__.py
alchemy/core/main.py
alchemy/core/models.py
alchemy/core/responses.py
alchemy/core/types.py
alchemy/nft/__init__.py
alchemy/nft/main.py
alchemy/nft/models.py
alchemy/nft/raw.py
alchemy/nft/responses.py
alchemy/nft/types.py
alchemy/nft/utils.py
alchemy/transact/__init__.py
alchemy/transact/main.py
alchemy/transact/types.py
alchemy_sdk-0.1.1.dist-info/METADATA
alchemy_sdk-0.1.1.dist-info/WHEEL
alchemy_sdk-0.1.1.dist-info/top_level.txt
alchemy_sdk-0.1.1.dist-info/RECORD
