Metadata-Version: 2.1
Name: alchemy-sdk
Version: 0.1.1
Summary: UNKNOWN
Home-page: https://github.com/alchemyplatform/alchemy-sdk-py
Author: Alchemy
License: MIT
Platform: UNKNOWN
Classifier: Development Status :: 2 - Pre-Alpha
Classifier: Intended Audience :: Developers
Classifier: License :: OSI Approved :: MIT License
Classifier: Programming Language :: Python :: 3.7
Classifier: Programming Language :: Python :: 3.8
Classifier: Programming Language :: Python :: 3.9
Classifier: Programming Language :: Python :: 3.10
Classifier: Programming Language :: Python :: 3.11
Requires-Python: >=3.7
